[
    {
        "날짜":"2022.01.24",
        "종가":75000,
        "전일비":-600,
        "시가":75400,
        "고가":75800,
        "저가":74700,
        "거래량":8013306
    },
    {
        "날짜":"2022.01.21",
        "종가":75600,
        "전일비":-900,
        "시가":75800,
        "고가":75800,
        "저가":74700,
        "거래량":15774888
    },
    {
        "날짜":"2022.01.20",
        "종가":76500,
        "전일비":200,
        "시가":76200,
        "고가":76700,
        "저가":75900,
        "거래량":9708168
    },
    {
        "날짜":"2022.01.19",
        "종가":76300,
        "전일비":-700,
        "시가":76500,
        "고가":76900,
        "저가":76100,
        "거래량":10598290
    },
    {
        "날짜":"2022.01.18",
        "종가":77000,
        "전일비":-500,
        "시가":77600,
        "고가":77800,
        "저가":76600,
        "거래량":9592788
    },
    {
        "날짜":"2022.01.17",
        "종가":77500,
        "전일비":200,
        "시가":77600,
        "고가":77800,
        "저가":76900,
        "거래량":8785122
    },
    {
        "날짜":"2022.01.14",
        "종가":77300,
        "전일비":-600,
        "시가":77700,
        "고가":78100,
        "저가":77100,
        "거래량":10096725
    },
    {
        "날짜":"2022.01.13",
        "종가":77900,
        "전일비":-1000,
        "시가":79300,
        "고가":79300,
        "저가":77900,
        "거래량":13889401
    },
    {
        "날짜":"2022.01.12",
        "종가":78900,
        "전일비":0,
        "시가":79500,
        "고가":79600,
        "저가":78600,
        "거래량":11000502
    },
    {
        "날짜":"2022.01.11",
        "종가":78900,
        "전일비":900,
        "시가":78400,
        "고가":79000,
        "저가":78000,
        "거래량":13221123
    },
    {
        "날짜":"2022.01.10",
        "종가":78000,
        "전일비":-300,
        "시가":78100,
        "고가":78100,
        "저가":77100,
        "거래량":9947422
    },
    {
        "날짜":"2022.01.07",
        "종가":78300,
        "전일비":1400,
        "시가":78100,
        "고가":78400,
        "저가":77400,
        "거래량":15163757
    },
    {
        "날짜":"2022.01.06",
        "종가":76900,
        "전일비":-500,
        "시가":76700,
        "고가":77600,
        "저가":76600,
        "거래량":12931954
    },
    {
        "날짜":"2022.01.05",
        "종가":77400,
        "전일비":-1300,
        "시가":78800,
        "고가":79000,
        "저가":76400,
        "거래량":25470640
    },
    {
        "날짜":"2022.01.04",
        "종가":78700,
        "전일비":100,
        "시가":78800,
        "고가":79200,
        "저가":78300,
        "거래량":12427416
    },
    {
        "날짜":"2022.01.03",
        "종가":78600,
        "전일비":300,
        "시가":79400,
        "고가":79800,
        "저가":78200,
        "거래량":13502112
    },
    {
        "날짜":"2021.12.30",
        "종가":78300,
        "전일비":-500,
        "시가":78900,
        "고가":79500,
        "저가":78100,
        "거래량":14236700
    },
    {
        "날짜":"2021.12.29",
        "종가":78800,
        "전일비":-1500,
        "시가":80200,
        "고가":80200,
        "저가":78500,
        "거래량":19794795
    },
    {
        "날짜":"2021.12.28",
        "종가":80300,
        "전일비":100,
        "시가":80200,
        "고가":80400,
        "저가":79700,
        "거래량":18226325
    },
    {
        "날짜":"2021.12.27",
        "종가":80200,
        "전일비":-300,
        "시가":80600,
        "고가":80600,
        "저가":79800,
        "거래량":10783368
    },
    {
        "날짜":"2021.12.24",
        "종가":80500,
        "전일비":600,
        "시가":80200,
        "고가":80800,
        "저가":80200,
        "거래량":12086380
    },
    {
        "날짜":"2021.12.23",
        "종가":79900,
        "전일비":500,
        "시가":79800,
        "고가":80000,
        "저가":79300,
        "거래량":13577498
    },
    {
        "날짜":"2021.12.22",
        "종가":79400,
        "전일비":1300,
        "시가":78900,
        "고가":79400,
        "저가":78800,
        "거래량":17105892
    },
    {
        "날짜":"2021.12.21",
        "종가":78100,
        "전일비":1000,
        "시가":77900,
        "고가":78300,
        "저가":77500,
        "거래량":14245298
    },
    {
        "날짜":"2021.12.20",
        "종가":77100,
        "전일비":-900,
        "시가":77600,
        "고가":77800,
        "저가":76800,
        "거래량":11264375
    },
    {
        "날짜":"2021.12.17",
        "종가":78000,
        "전일비":200,
        "시가":76800,
        "고가":78000,
        "저가":76800,
        "거래량":13108479
    },
    {
        "날짜":"2021.12.16",
        "종가":77800,
        "전일비":200,
        "시가":78500,
        "고가":78500,
        "저가":77400,
        "거래량":11996128
    },
    {
        "날짜":"2021.12.15",
        "종가":77600,
        "전일비":600,
        "시가":76400,
        "고가":77600,
        "저가":76300,
        "거래량":9584939
    },
    {
        "날짜":"2021.12.14",
        "종가":77000,
        "전일비":200,
        "시가":76500,
        "고가":77200,
        "저가":76200,
        "거래량":10976660
    },
    {
        "날짜":"2021.12.13",
        "종가":76800,
        "전일비":-100,
        "시가":77200,
        "고가":78300,
        "저가":76500,
        "거래량":15038750
    },
    {
        "날짜":"2021.12.10",
        "종가":76900,
        "전일비":-1300,
        "시가":77400,
        "고가":77600,
        "저가":76800,
        "거래량":9155219
    },
    {
        "날짜":"2021.12.09",
        "종가":78200,
        "전일비":800,
        "시가":77400,
        "고가":78200,
        "저가":77000,
        "거래량":21604528
    },
    {
        "날짜":"2021.12.08",
        "종가":77400,
        "전일비":0,
        "시가":78300,
        "고가":78600,
        "저가":77100,
        "거래량":21558340
    },
    {
        "날짜":"2021.12.07",
        "종가":77400,
        "전일비":1100,
        "시가":76100,
        "고가":77700,
        "저가":75600,
        "거래량":19232453
    },
    {
        "날짜":"2021.12.06",
        "종가":76300,
        "전일비":700,
        "시가":75100,
        "고가":76700,
        "저가":74900,
        "거래량":16391250
    },
    {
        "날짜":"2021.12.03",
        "종가":75600,
        "전일비":-200,
        "시가":75600,
        "고가":76000,
        "저가":74100,
        "거래량":18330240
    },
    {
        "날짜":"2021.12.02",
        "종가":75800,
        "전일비":1400,
        "시가":73900,
        "고가":75800,
        "저가":73800,
        "거래량":23652940
    },
    {
        "날짜":"2021.12.01",
        "종가":74400,
        "전일비":3100,
        "시가":72000,
        "고가":74800,
        "저가":71600,
        "거래량":21954856
    },
    {
        "날짜":"2021.11.30",
        "종가":71300,
        "전일비":-1000,
        "시가":73200,
        "고가":73900,
        "저가":70500,
        "거래량":30364841
    },
    {
        "날짜":"2021.11.29",
        "종가":72300,
        "전일비":0,
        "시가":71700,
        "고가":73000,
        "저가":71400,
        "거래량":16682559
    },
    {
        "날짜":"2021.11.26",
        "종가":72300,
        "전일비":-1400,
        "시가":73500,
        "고가":74100,
        "저가":72000,
        "거래량":13002242
    },
    {
        "날짜":"2021.11.25",
        "종가":73700,
        "전일비":-1100,
        "시가":75100,
        "고가":75100,
        "저가":73600,
        "거래량":12559258
    },
    {
        "날짜":"2021.11.24",
        "종가":74800,
        "전일비":-500,
        "시가":76000,
        "고가":76200,
        "저가":74100,
        "거래량":15652305
    },
    {
        "날짜":"2021.11.23",
        "종가":75300,
        "전일비":400,
        "시가":76000,
        "고가":76000,
        "저가":74500,
        "거래량":22029195
    },
    {
        "날짜":"2021.11.22",
        "종가":74900,
        "전일비":3700,
        "시가":73300,
        "고가":75200,
        "저가":73000,
        "거래량":27506623
    },
    {
        "날짜":"2021.11.19",
        "종가":71200,
        "전일비":1000,
        "시가":70400,
        "고가":71400,
        "저가":70100,
        "거래량":11954728
    },
    {
        "날짜":"2021.11.18",
        "종가":70200,
        "전일비":-500,
        "시가":70700,
        "고가":71000,
        "저가":70200,
        "거래량":10144957
    },
    {
        "날짜":"2021.11.17",
        "종가":70700,
        "전일비":-600,
        "시가":71300,
        "고가":71600,
        "저가":70600,
        "거래량":11027606
    },
    {
        "날짜":"2021.11.16",
        "종가":71300,
        "전일비":-100,
        "시가":71500,
        "고가":72000,
        "저가":71300,
        "거래량":10919239
    },
    {
        "날짜":"2021.11.15",
        "종가":71400,
        "전일비":800,
        "시가":71700,
        "고가":71900,
        "저가":70900,
        "거래량":12420710
    },
    {
        "날짜":"2021.11.12",
        "종가":70600,
        "전일비":700,
        "시가":70200,
        "고가":70900,
        "저가":69900,
        "거래량":10087450
    },
    {
        "날짜":"2021.11.11",
        "종가":69900,
        "전일비":-300,
        "시가":69900,
        "고가":70000,
        "저가":69600,
        "거래량":11489122
    },
    {
        "날짜":"2021.11.10",
        "종가":70200,
        "전일비":-300,
        "시가":70300,
        "고가":70900,
        "저가":70200,
        "거래량":9422009
    },
    {
        "날짜":"2021.11.09",
        "종가":70500,
        "전일비":-100,
        "시가":70300,
        "고가":71000,
        "저가":70100,
        "거래량":11159589
    },
    {
        "날짜":"2021.11.08",
        "종가":70600,
        "전일비":400,
        "시가":70400,
        "고가":70600,
        "저가":69800,
        "거래량":11121981
    },
    {
        "날짜":"2021.11.05",
        "종가":70200,
        "전일비":-400,
        "시가":71600,
        "고가":71600,
        "저가":70200,
        "거래량":12667743
    },
    {
        "날짜":"2021.11.04",
        "종가":70600,
        "전일비":200,
        "시가":71200,
        "고가":71600,
        "저가":70500,
        "거래량":11818987
    },
    {
        "날짜":"2021.11.03",
        "종가":70400,
        "전일비":-1100,
        "시가":71700,
        "고가":71700,
        "저가":70100,
        "거래량":12770428
    },
    {
        "날짜":"2021.11.02",
        "종가":71500,
        "전일비":1600,
        "시가":70800,
        "고가":72200,
        "저가":70700,
        "거래량":16812570
    },
    {
        "날짜":"2021.11.01",
        "종가":69900,
        "전일비":100,
        "시가":70200,
        "고가":70600,
        "저가":69900,
        "거래량":11503729
    },
    {
        "날짜":"2021.10.29",
        "종가":69800,
        "전일비":-900,
        "시가":71200,
        "고가":71600,
        "저가":69700,
        "거래량":17016151
    },
    {
        "날짜":"2021.10.28",
        "종가":70700,
        "전일비":600,
        "시가":69500,
        "고가":72200,
        "저가":69500,
        "거래량":20644902
    },
    {
        "날짜":"2021.10.27",
        "종가":70100,
        "전일비":-1000,
        "시가":71000,
        "고가":71000,
        "저가":70000,
        "거래량":10295316
    },
    {
        "날짜":"2021.10.26",
        "종가":71100,
        "전일비":900,
        "시가":70600,
        "고가":71500,
        "저가":70400,
        "거래량":10528252
    },
    {
        "날짜":"2021.10.25",
        "종가":70200,
        "전일비":-200,
        "시가":69900,
        "고가":70600,
        "저가":69500,
        "거래량":10029621
    },
    {
        "날짜":"2021.10.22",
        "종가":70400,
        "전일비":200,
        "시가":70000,
        "고가":70700,
        "저가":70000,
        "거래량":8395448
    },
    {
        "날짜":"2021.10.21",
        "종가":70200,
        "전일비":-100,
        "시가":70300,
        "고가":70600,
        "저가":70000,
        "거래량":10891094
    },
    {
        "날짜":"2021.10.20",
        "종가":70300,
        "전일비":-300,
        "시가":70700,
        "고가":71000,
        "저가":70200,
        "거래량":10151638
    },
    {
        "날짜":"2021.10.19",
        "종가":70600,
        "전일비":400,
        "시가":70800,
        "고가":71000,
        "저가":70400,
        "거래량":9507991
    },
    {
        "날짜":"2021.10.18",
        "종가":70200,
        "전일비":100,
        "시가":70200,
        "고가":70300,
        "저가":69200,
        "거래량":13486391
    },
    {
        "날짜":"2021.10.15",
        "종가":70100,
        "전일비":700,
        "시가":70200,
        "고가":71000,
        "저가":70000,
        "거래량":18051612
    },
    {
        "날짜":"2021.10.14",
        "종가":69400,
        "전일비":600,
        "시가":69000,
        "고가":69800,
        "저가":68800,
        "거래량":19520641
    },
    {
        "날짜":"2021.10.13",
        "종가":68800,
        "전일비":-200,
        "시가":68700,
        "고가":69600,
        "저가":68300,
        "거래량":24172015
    },
    {
        "날짜":"2021.10.12",
        "종가":69000,
        "전일비":-2500,
        "시가":70700,
        "고가":70900,
        "저가":68700,
        "거래량":31001484
    },
    {
        "날짜":"2021.10.08",
        "종가":71500,
        "전일비":-100,
        "시가":72300,
        "고가":72400,
        "저가":71500,
        "거래량":14043287
    },
    {
        "날짜":"2021.10.07",
        "종가":71600,
        "전일비":300,
        "시가":71600,
        "고가":72100,
        "저가":71300,
        "거래량":13683532
    },
    {
        "날짜":"2021.10.06",
        "종가":71300,
        "전일비":-900,
        "시가":72600,
        "고가":72800,
        "저가":71200,
        "거래량":18956962
    },
    {
        "날짜":"2021.10.05",
        "종가":72200,
        "전일비":-1000,
        "시가":73000,
        "고가":73000,
        "저가":71400,
        "거래량":24013921
    },
    {
        "날짜":"2021.10.01",
        "종가":73200,
        "전일비":-900,
        "시가":73900,
        "고가":74000,
        "저가":72900,
        "거래량":15803395
    },
    {
        "날짜":"2021.09.30",
        "종가":74100,
        "전일비":0,
        "시가":74300,
        "고가":74800,
        "저가":73700,
        "거래량":19919361
    },
    {
        "날짜":"2021.09.29",
        "종가":74100,
        "전일비":-2200,
        "시가":74800,
        "고가":75300,
        "저가":73800,
        "거래량":23992458
    },
    {
        "날짜":"2021.09.28",
        "종가":76300,
        "전일비":-1400,
        "시가":77700,
        "고가":77800,
        "저가":76200,
        "거래량":15406382
    },
    {
        "날짜":"2021.09.27",
        "종가":77700,
        "전일비":400,
        "시가":77300,
        "고가":77700,
        "저가":77000,
        "거래량":11699798
    },
    {
        "날짜":"2021.09.24",
        "종가":77300,
        "전일비":-100,
        "시가":77600,
        "고가":77700,
        "저가":77100,
        "거래량":12247274
    },
    {
        "날짜":"2021.09.23",
        "종가":77400,
        "전일비":200,
        "시가":77500,
        "고가":77600,
        "저가":76800,
        "거래량":17055590
    },
    {
        "날짜":"2021.09.17",
        "종가":77200,
        "전일비":1100,
        "시가":76300,
        "고가":77200,
        "저가":75900,
        "거래량":16289502
    },
    {
        "날짜":"2021.09.16",
        "종가":76100,
        "전일비":-900,
        "시가":77300,
        "고가":77400,
        "저가":76100,
        "거래량":13067622
    },
    {
        "날짜":"2021.09.15",
        "종가":77000,
        "전일비":400,
        "시가":77400,
        "고가":77400,
        "저가":76400,
        "거래량":12829128
    },
    {
        "날짜":"2021.09.14",
        "종가":76600,
        "전일비":300,
        "시가":77100,
        "고가":77700,
        "저가":76600,
        "거래량":18167057
    },
    {
        "날짜":"2021.09.13",
        "종가":76300,
        "전일비":1000,
        "시가":75200,
        "고가":76300,
        "저가":75100,
        "거래량":11397775
    }
]